{
  "main": {
    "id": "5e3a2c08fd86cbf6",
    "type": "split",
    "children": [
      {
        "id": "d0301d2fb211fd6e",
        "type": "tabs",
        "children": [
          {
            "id": "83e9dd39a440e824",
            "type": "leaf",
            "state": {
              "type": "markdown",
              "state": {
                "file": "2.Areas/stylelint, prettier 설치 및 설정.md",
                "mode": "source",
                "backlinks": true,
                "source": true
              }
            }
          }
        ]
      }
    ],
    "direction": "vertical"
  },
  "left": {
    "id": "6a36edb9794a6609",
    "type": "split",
    "children": [
      {
        "id": "1c1c49334377bf45",
        "type": "tabs",
        "children": [
          {
            "id": "a6f314c8c599f3ee",
            "type": "leaf",
            "state": {
              "type": "file-explorer",
              "state": {
                "sortOrder": "alphabetical"
              }
            }
          },
          {
            "id": "c244d9cf0f8a0b58",
            "type": "leaf",
            "state": {
              "type": "search",
              "state": {
                "query": "tag:#todo/실행컨텍스트",
                "matchingCase": false,
                "explainSearch": false,
                "collapseAll": false,
                "extraContext": false,
                "sortOrder": "alphabetical"
              }
            }
          },
          {
            "id": "2ad2b2a8a78cfaeb",
            "type": "leaf",
            "state": {
              "type": "bookmarks",
              "state": {}
            }
          }
        ]
      }
    ],
    "direction": "horizontal",
    "width": 313.5110321044922
  },
  "right": {
    "id": "065d8a4f3451fb00",
    "type": "split",
    "children": [
      {
        "id": "dc3386b664894eca",
        "type": "tabs",
        "children": [
          {
            "id": "2b4484155cb7c555",
            "type": "leaf",
            "state": {
              "type": "backlink",
              "state": {
                "file": "2.Areas/stylelint, prettier 설치 및 설정.md",
                "collapseAll": false,
                "extraContext": false,
                "sortOrder": "alphabetical",
                "showSearch": false,
                "searchQuery": "",
                "backlinkCollapsed": false,
                "unlinkedCollapsed": true
              }
            }
          },
          {
            "id": "d3f2680a952b6b2e",
            "type": "leaf",
            "state": {
              "type": "outgoing-link",
              "state": {
                "file": "2.Areas/stylelint, prettier 설치 및 설정.md",
                "linksCollapsed": false,
                "unlinkedCollapsed": true
              }
            }
          },
          {
            "id": "9261e3f3a2ece847",
            "type": "leaf",
            "state": {
              "type": "tag",
              "state": {
                "sortOrder": "frequency",
                "useHierarchy": true
              }
            }
          },
          {
            "id": "d5917f7304d3ff7b",
            "type": "leaf",
            "state": {
              "type": "outline",
              "state": {
                "file": "2.Areas/stylelint, prettier 설치 및 설정.md"
              }
            }
          }
        ],
        "currentTab": 2
      }
    ],
    "direction": "horizontal",
    "width": 300,
    "collapsed": true
  },
  "left-ribbon": {
    "hiddenItems": {
      "switcher:퀵 스위처 열기": false,
      "graph:그래프 뷰 열기": false,
      "canvas:새 캔버스 만들기": false,
      "daily-notes:오늘의 데일리 노트 열기": false,
      "templates:템플릿 삽입": false,
      "command-palette:명령어 팔레트 열기": false,
      "workspaces:작업 공간 레이아웃 관리": false
    }
  },
  "active": "83e9dd39a440e824",
  "lastOpenFiles": [
    "Files/Pasted image 20231031232154.png",
    "2.Areas/stylelint, prettier 설치 및 설정.md",
    "3.Resources/강의/Kimbug_SASS/(Kimbug SASS) 2. Node 및 node-sass 개발 환경 설정.md",
    "3.Resources/강의/Kimbug_SASS/README (작성 후 GitHub으로 이동).md",
    "3.Resources/강의/Kimbug_SASS/(Kimbug SASS) 1. 강의 자료.md",
    "Files/imageFrom생활코딩-Float.png",
    "3.Resources/강의/Kimbug_SASS/README.md",
    "3.Resources/강의/Kimbug_SASS/(KimBug SASS).md",
    "3.Resources/강의/Kimbug_funnyCSS/FunnyCSS - Kimbug.md",
    "2.Areas/기록법/제텔카스텐_슬기로운메모생활/제텔카스텐 - 3부. 성공적인 글쓰기에 이르는 여섯 단계.md",
    "3.Resources/강의/Kimbug_SASS",
    "2.Areas/기록법/제텔카스텐_슬기로운메모생활/제텔카스텐 - 2부. 네 가지 기본 원칙.md",
    "2.Areas/기록법/제텔카스텐_슬기로운메모생활/제텔카스텐 - 1부. 도입.md",
    "3.Resources/책/책.md",
    "3.Resources/책/모던 자바스크립트/모던 자바스크립트 DeepDive.md",
    "2.Areas/기록법/제텔카스텐_슬기로운메모생활",
    "1.Projects/자바스크립트/- 클로저를 이해하려면 실행컨텍스트와 스코프체인을 먼저 이해해야 합니다.md",
    "3.Resources/책/모던 자바스크립트",
    "3.Resources/책/모던 자바스크립트/모던 자바스크립트 DeepDive - 9장. 타입 변환과 단축 평가.md",
    "3.Resources/책/모던 자바스크립트/모던 자바스크립트 DeepDive - 45장. 프로미스.md",
    "3.Resources/강의/Kimbug_funnyCSS/FunnyCSS_6.Flex.md",
    "Files/imageFrom김버그CSS_alignContent.png",
    "Files/imageFrom김버그CSS_alignItems.png",
    "Files/imageFrom김버그CSS_z-index.png",
    "3.Resources/강의/Kimbug_funnyCSS/FunnyCSS_3.Box.md",
    "3.Resources/강의/Kimbug_funnyCSS/FunnyCSS_5.Position.md",
    "1.Projects/자바스크립트/자바스크립트 호이스팅.md",
    "1.Projects/CSS/CSS 선택자 우선순위.md",
    "1.Projects/CSS/CSS 동적 가상 클래스 선택자.md",
    "1.Projects/CSS/CSS 구조적 가상 클래스 선택자.md",
    "3.Resources/강의/Kimbug_funnyCSS/FunnyCSS_4.Float.md",
    "Files/imageFrom김버그CSS_float.png",
    "1.Projects/CSS/@CSS 요약집 만들자.md",
    "3.Resources/강의/Kimbug_funnyCSS/FunnyCSS_2.Selectors (선택자).md",
    "새 텍스트 문서.txt",
    "Files/20231010_CSS_Box_Model.png",
    "3.Resources/강의",
    "3.Resources/강의/Kimbug_funnyCSS",
    "1.Projects/CSS",
    "3.Resources/책",
    "Templates",
    "2.Areas/기록법/옵시디언"
  ]
}